{
"year": "2015",
"metaSession": "",
"pdf1page": "http://editions-rnti.fr/render_pdf.php?p1&p=1002112",
"pdfarticle": "",
"abstract": "For social network analysis, existing centrality measures emphasize the importance of an actor considering only the structural position in the network regardless of a priori information on this actors such as popularity, accessibility or behavior. In this study new variants of centrality measures are proposed operating both the network structure and the specific attributes of an actor. Experiments have validated the contribution of valuations especially for the detection of broadcasters in social networks.",
"title": "Mesure d'influence via les indicateurs de centralité dans les réseaux sociaux",
"placeAut":[{
"place":"Saint-Etienne",
"country":"France",
"location":{
	"lat":"45.439695",
	"lon":"4.3871779"
}
}],
"series": "Revue des Nouvelles Technologies de l'Information",
"location": "{u'lat': 49.815273, u'lon': 6.129582999999999}",
"place": "Luxembourg",
"booktitle": "EGC",
"idArt": "39",
"authors": "['Oualid Benyahia','Christine Largeron']"
}